{
  "main": {
    "projects": [
      {
        "id": 9,
        "img": "./../projects/controlstock/logostock.png",
        "name": "Control de Stock",
        "description": "Inventory management and control system with barcode reader for clothing store",
        "descriptionES": "Sistema de gestion y control de inventario con lector de código de barras para tienda de ropa",
        "marginTop": "2px",
        "data": {
          "desc": "In this project, an inventory control system with a barcode was developed, in this system you can add, edit, delete and send products to other branches of the same brand, it also has its own panel used so that sellers can only access to the info. they need to make a sale. among those things it has other great features that help stores to better manage their store",
          "descES": "En este proyecto se desarrollo un sistema de control de inventario con código de barra, en este sistema se puede agregar, editar, eliminar y enviar productos a otras sucursales de la misma marca , tambien tiene su propio panel empleado para que los vendedores solo puedan acceder a la info. que necesitan para hacer una venta. entre esas cosas tiene otras funcionalidadea geniales que ayudan a las tiendas a llevar un mejor manejo de su tienda",
          "images": [
            {
              "id": 1,
              "img":"./../projects/controlstock/controlstock1.png"
            },
            {
              "id": 2,
              "img":"./../projects/controlstock/controlstock2.png"
            },
            {
              "id": 3,
              "img":"./../projects/controlstock/controlstock3.png"
            },
            {
              "id": 4,
              "img":"./../projects/controlstock/controlstock4.png"
            },
            {
              "id": 5,
              "img":  "./../projects/controlstock/controlstock5.png"
            }
        
          ]
         
         
         
         
         
   
        }
      },
      {
        "id": 10,
        "img": "./../projects/webarchitect/logoarq.png",
        "name": "Felix T. Clavijo",
        "description": "Website for the Felix Clavijo architecture studio team",
        "descriptionES": "Página web para el equipo del estudio de arquitectura Felix Clavijo",
        "marginTop": "90px",
        "data": {
          "repo": "",
          "deploy": "https://arquitectofelixclavijo.com",
          "desc": "A personalized web page was built to represent the study of the architect Felix Clavijo, where it contains the necessary information, Works, Designs, projects, etc. It was built in a responsive way for cell phones and computers as well, before programming it, a design approved by the client was created.",
          "descES": "Se construyo una Página web personalizada para representar el estudio del Arquitecto Felix Clavijo, donde contiene la información necesaria, Trabajos,  Diseños, proyectos, etc. Fue construida de manera responsive para celulares y computadoras tambien antes de programarla se le creo un diseño aprobado por el cliente.",
          "images": [
            {
              "id": 1,
              "img": "./../projects/webarchitect/webarq1.png"
            },
            {
              "id": 2,
              "img": "./../projects/webarchitect/webarq2.png"
            },
            {
              "id": 3,
              "img": "./../projects/webarchitect/webarq3.png"
            },
            {
              "id": 4,
              "img": "./../projects/webarchitect/webarq4.png"
            },
            {
              "id": 5,
              "img": "./../projects/webarchitect/webarq5.png"
            },
            {
              "id": 6,
              "img": "./../projects/webarchitect/webarq6.png"
            }
          ]
        }
      },
      {
        "id": 1,
        "img": "./../projects/amazon/amazonhome.jpg",
        "name": "Amazon Clone",
        "description": "This is a Amazon clone built in 100% react with method of payment and using the hosting in firebase",
        "descriptionES": "Este es un Clon de Amazon contruido al 100% en react, utilizando metodos de pago y el hosting de firebase",
        "marginTop": "2px",
        "data": {
          "repo": "https://github.com/ayelen3976/amazon-clone",
          "deploy": "https://challenge-c052e.web.app/ ",
          "tecnologies": "",
   
          "images": [
            {
              "id": 1,
              "img": "./../projects/amazon/amazon1.png"
            },
            {
              "id": 2,
              "img":"./../projects/amazon/amazon2.png"
            },
            {
              "id": 3,
              "img":"./../projects/amazon/amazon3.png"
            },
            {
              "id": 4,
              "img":"./../projects/amazon/amazon4.png"
            },
            {
              "id": 5,
              "img":"./../projects/amazon/amazon5.png"
            },
            {
              "id": 6,
              "img":"./../projects/amazon/amazon6.png"
            },
            {
              "id": 7,
              "img":"./../projects/amazon/amazon7.png"
            }
        
        
          ]
        }
      },
      {
        "id": 2,
        "img": "./../projects/netflix/netflixhome.jpg",
        "name": "Netflix Clone",
        "description": "This is a Netflix Clone using the TMDb api, built in 100% react on the client side",
        "descriptionES": "Este es un Clon de Netflix utilizando la api de TMDb, construido al 100% en react",
        "marginTop": "90px",
        "data": {
          "repo": "https://github.com/ayelen3976/netflix--clone",
          "deploy": "https://netflix-clone-alpha.vercel.app/",
       
          "images": [
            {
              "id": 1,
              "img":  "./../projects/netflix/netflix1.png"
            },
            {
              "id": 2,
              "img": "./../projects/netflix/netflix2.png"
            },
            {
              "id": 3,
              "img": "./../projects/netflix/netflix3.png"
            }
       
        
          ]
        }
      },
      {
        "id": 3,
        "img": "./../projects/moscow/moscowhome.png",
        "name": "Moscow Diet",
        "description": "Final project carried out in henry's bootcamp, consisted of building an e-commerce working as a fullstack developer",
        "descriptionES": "Proyecto final de henry bootcamp, consistió en construir un e-commerce fullstack",
        "marginTop": "2px",
        "data": {
          "repo": "https://github.com/ayelen3976/E-commerce/tree/last",
          "images": [
            {
              "id": 1,
              "img": "./../projects/moscow/moscow1.png"
            },
            {
              "id": 2,
              "img":"./../projects/moscow/moscow2.png"
            },
            {
              "id": 3,
              "img":"./../projects/moscow/moscow3.png"
            },
            {
              "id": 4,
              "img":"./../projects/moscow/moscow4.png"
            },
            {
              "id": 5,
              "img":"./../projects/moscow/moscow5.png"
            },
            {
              "id": 6,
              "img":"./../projects/moscow/moscow6.png"
            },
            {
              "id": 7,
              "img":"./../projects/moscow/moscow7.png"
            },
            {
              "id": 8,
              "img":"./../projects/moscow/moscow8.png"
            },
            {
              "id": 9,
              "img":"./../projects/moscow/moscow9.png"
            },
            {
              "id": 10,
              "img":"./../projects/moscow/moscow10.png"
            },
            {
              "id": 11,
              "img":"./../projects/moscow/moscow11.png"
            },  {
              "id": 12,
              "img":"./../projects/moscow/moscow12.png"
            }
        
        
          ]
       
        }
      },
      {
        "id": 4,
        "img": "./../projects/weather/weatherhome.jpg",
        "name": "Weather Week",
        "description": "Small project that consists of seeing the climate of the next 5 days of different countries",
        "descriptionES": "Pequeño proyecto que consiste en mirar el clima de los próximos 5 días en diferentes países",
        "data": {
          "repo": "https://github.com/ayelen3976/weather-week",
          "deploy": "https://client-theta-green.vercel.app/",
          "images": [
            {
              "id": 1,
              "img":"./../projects/weather/weather1.png"
            },
            {
              "id": 2,
              "img":"./../projects/weather/weather2.png"
            },
            {
              "id": 3,
              "img":"./../projects/weather/weather3.png"
            }
 
        
        
        
          ]
       
        }
      },
      {
        "id": 5,
        "img": "./../projects/dtodo/dtodohome.jpg",
        "name": "DTodoInd",
        "description": "E-commerce full stack for a real clothing store in Argentina in process ",
        "descriptionES": "Tienda online para una tienda real de Argentina, que vende indumentaria",
        "data": {
          "repo": "https://github.com/Bhavesh588/manjares",
          "deploy": "https://www.dtodoind.com/",
          "images": [
            {
              "id": 1,
              "img":  "./../projects/dtodo/dtodo1.png"
            },
            {
              "id": 2,
              "img": "./../projects/dtodo/dtodo2.png"
            },
            {
              "id": 3,
              "img": "./../projects/dtodo/dtodo3.png"
            },
            {
              "id": 4,
              "img": "./../projects/dtodo/dtodo4.png"
            },
            {
              "id": 5,
              "img": "./../projects/dtodo/dtodo5.png"
            },
            {
              "id": 6,
              "img": "./../projects/dtodo/dtodo6.png"
            },
            {
              "id": 7,
              "img": "./../projects/dtodo/dtodo7.png"
            },
            {
              "id": 8,
              "img": "./../projects/dtodo/dtodo8.png"
            },
            {
              "id": 9,
              "img": "./../projects/dtodo/dtodo9.png"
            },
            {
              "id": 10,
              "img": "./../projects/dtodo/dtodo10.png"
            },
            {
              "id": 11,
              "img": "./../projects/dtodo/dtodo11.png"
            },  {
              "id": 12,
              "img": "./../projects/dtodo/dtodo12.png"
            },      {
              "id": 13,
              "img": "./../projects/dtodo/dtodo13.png"
            },
            {
              "id": 14,
              "img": "./../projects/dtodo/dtodo14.png"
            },
            {
              "id": 15,
              "img": "./../projects/dtodo/dtodo15.png"
            },
            {
              "id": 16,
              "img": "./../projects/dtodo/dtodo16.png"
            },
            {
              "id": 17,
              "img": "./../projects/dtodo/dtodo17.png"
            },
            {
              "id": 18,
              "img": "./../projects/dtodo/dtodo18.jpg"
            }
        
        
          ]
     
        }
      },
      {
        "id": 6,
        "img": "./../projects/somosmas/somosmashome.jpg",
        "name": "Somos Más",
        "description": "Project carried out in the alkemy program to gain experience as a junior developer",
        "descriptionES": "Proyecto llevado a cabo en el programa de alkemy para obtener experiencia como developer junior",
        "data": {
          "images": [
            {
              "id": 1,
              "img":"./../projects/somosmas/somosmas1.png"
            },
            {
              "id": 2,
              "img":"./../projects/somosmas/somosmas2.png"
            },
            {
              "id": 3,
              "img":"./../projects/somosmas/somosmas3.png"
            },
            {
              "id": 4,
              "img":"./../projects/somosmas/somosmas4.png"
            },
            {
              "id": 5,
              "img":"./../projects/somosmas/somosmas5.png"
            },
            {
              "id": 6,
              "img":"./../projects/somosmas/somosmas6.png"
            },
            {
              "id": 7,
              "img":"./../projects/somosmas/somosmas7.png"
            },
            {
              "id": 8,
              "img":"./../projects/somosmas/somosmas8.png"
            }
           
        
          ]
      
        }
      },
      {
        "id": 7,
        "img": "./../projects/mine/mine.png",
        "name": "Personal Portfolio",
        "description": "This website, check the repository! :)",
        "descriptionES": "Esta es mi pagina, puede chequear el repositorio ! :)",
        "data": {
          "repo": "https://github.com/ayelen3976/web-ayelen.git",
          "deploy": "https://portfolio-c470d.web.app/",
          "images": [
            {
              "id": 1,
              "img":"./../projects/mine/mine1.png"
            },
            {
              "id": 2,
              "img":"./../projects/mine/mine2.png"
            }
        
          ]

        }
      },
      {
        "id": 8,
        "img": "./../projects/celPhone/celhome.png",
        "name": "Project in Java",
        "description": "It was my first project in Java",
        "descriptionES": "Este fue mi primer proyecto en java , próximamente voy a construir una api",
        "data": {
          "repo": "https://github.com/ayelen3976/CelularesJava",
      
          "images": [
            {
              "id": 1,
              "img":"./../projects/celPhone/cel1.png"
            },
            {
              "id": 2,
              "img":"./../projects/celPhone/cel2.png"
            },
            {
              "id": 3,
              "img":"./../projects/celPhone/cel3.png"
            },
            {
              "id": 4,
              "img":"./../projects/celPhone/cel4.png"
            },
            {
              "id": 5,
              "img": "./../projects/celPhone/cel5.png"
            },
            {
              "id": 6,
              "img": "./../projects/celPhone/cel6.png"
            }
        
          ]
         
         
        }
      }
    ]
  }
}